{"type":"Feature","properties":{"type":"barangay","level":"4","label":"Dilausan, Maguing, Lanao del Sur, Autonomous Region of Muslim Mindanao (ARMM), PH","locale":"ph.autonomous-region-of-muslim-mindanao-armm.lanao-del-sur.maguing.dilausan","country_id":177,"country_reference":177,"country_name":"Philippines","region_id":"1","region_reference":"15","region_name":"Autonomous Region of Muslim Mindanao (ARMM)","province_id":"42","province_reference":"42","province_name":"Lanao del Sur","city_id":"766","city_reference":"836","city_name":"Maguing","barangay_id":"21597","barangay_reference":"20833","barangay_name":"Dilausan"},"geometry":{"type":"MultiPolygon","coordinates":[[[[124.387657,7.89361],[124.387894,7.89345],[124.388023,7.89325],[124.388268,7.89272],[124.388657,7.89278],[124.388893,7.89285],[124.389267,7.89238],[124.389618,7.89119],[124.390129,7.89069],[124.390549,7.89122],[124.390907,7.89172],[124.391113,7.89178],[124.391281,7.89135],[124.391357,7.89089],[124.391663,7.89066],[124.392067,7.89032],[124.392738,7.88996],[124.393082,7.88956],[124.393349,7.88913],[124.393883,7.8887],[124.39418,7.88196],[124.391907,7.88229],[124.390312,7.88279],[124.386742,7.8881],[124.387657,7.89361]]]]}}