{"type":"Feature","properties":{"type":"barangay","level":"4","label":"Macaguiling, Binidayan, Lanao del Sur, Autonomous Region of Muslim Mindanao (ARMM), PH","locale":"ph.autonomous-region-of-muslim-mindanao-armm.lanao-del-sur.binidayan.macaguiling","country_id":177,"country_reference":177,"country_name":"Philippines","region_id":"1","region_reference":"15","region_name":"Autonomous Region of Muslim Mindanao (ARMM)","province_id":"42","province_reference":"42","province_name":"Lanao del Sur","city_id":"206","city_reference":"818","city_name":"Binidayan","barangay_id":"5374","barangay_reference":"20430","barangay_name":"Macaguiling"},"geometry":{"type":"MultiPolygon","coordinates":[[[[124.160797,7.80869],[124.157463,7.80642],[124.156403,7.79988],[124.15274,7.80072],[124.153938,7.80825],[124.155357,7.80875],[124.156342,7.80897],[124.156929,7.80905],[124.157539,7.80906],[124.159058,7.80893],[124.160004,7.80884],[124.160797,7.80869]]]]}}