{"type":"Feature","properties":{"type":"barangay","level":"4","label":"Niog-niog, Luuk, Sulu, Autonomous Region of Muslim Mindanao (ARMM), PH","locale":"ph.autonomous-region-of-muslim-mindanao-armm.sulu.luuk.niog-niog","country_id":177,"country_reference":177,"country_name":"Philippines","region_id":"1","region_reference":"15","region_name":"Autonomous Region of Muslim Mindanao (ARMM)","province_id":"74","province_reference":"74","province_name":"Sulu","city_id":"735","city_reference":"1479","city_name":"Luuk","barangay_id":"20606","barangay_reference":"38147","barangay_name":"Niog-niog"},"geometry":{"type":"MultiPolygon","coordinates":[[[[121.305717,5.97872],[121.316521,5.97941],[121.316864,5.979445],[121.319443,5.96419],[121.308731,5.96184],[121.307602,5.9674],[121.305717,5.97872]]]]}}