{"type":"Feature","properties":{"type":"barangay","level":"4","label":"Calaan, Buldon, Shariff Kabunsuan, Autonomous Region of Muslim Mindanao (ARMM), PH","locale":"ph.autonomous-region-of-muslim-mindanao-armm.shariff-kabunsuan.buldon.calaan","country_id":177,"country_reference":177,"country_name":"Philippines","region_id":"1","region_reference":"15","region_name":"Autonomous Region of Muslim Mindanao (ARMM)","province_id":"68","province_reference":"68","province_name":"Shariff Kabunsuan","city_id":"246","city_reference":"1399","city_name":"Buldon","barangay_id":"6480","barangay_reference":"36229","barangay_name":"Calaan"},"geometry":{"type":"MultiPolygon","coordinates":[[[[124.36731,7.51779],[124.375999,7.51667],[124.388557,7.51751],[124.387192,7.49339],[124.371361,7.4949],[124.371567,7.49619],[124.371429,7.49914],[124.369957,7.50249],[124.368561,7.50546],[124.368423,7.50761],[124.368713,7.50951],[124.36895,7.51221],[124.368088,7.51526],[124.36731,7.51779]]]]}}