{"type":"Feature","properties":{"type":"barangay","level":"4","label":"Lower Sampunay, Parang, Sulu, Autonomous Region of Muslim Mindanao (ARMM), PH","locale":"ph.autonomous-region-of-muslim-mindanao-armm.sulu.parang.lower-sampunay","country_id":177,"country_reference":177,"country_name":"Philippines","region_id":"1","region_reference":"15","region_name":"Autonomous Region of Muslim Mindanao (ARMM)","province_id":"74","province_reference":"74","province_name":"Sulu","city_id":"1002","city_reference":"1485","city_name":"Parang","barangay_id":"28350","barangay_reference":"38278","barangay_name":"Lower Sampunay"},"geometry":{"type":"MultiPolygon","coordinates":[[[[120.908669,5.95566],[120.913597,5.94683],[120.905869,5.94404],[120.905258,5.94441],[120.903214,5.94949],[120.902557,5.95351],[120.908669,5.95566]]]]}}