{"type":"Feature","properties":{"type":"barangay","level":"4","label":"Esperanza, San Andres, Catanduanes, Bicol Region (Region V), PH","locale":"ph.bicol-region-region-v.catanduanes.san-andres.esperanza","country_id":177,"country_reference":177,"country_name":"Philippines","region_id":"2","region_reference":"5","region_name":"Bicol Region (Region V)","province_id":"23","province_reference":"23","province_name":"Catanduanes","city_id":"1540","city_reference":"413","city_name":"San Andres","barangay_id":"31991","barangay_reference":"9801","barangay_name":"Esperanza"},"geometry":{"type":"MultiPolygon","coordinates":[[[[124.105957,13.59333],[124.106537,13.59312],[124.108002,13.592445],[124.109962,13.59186],[124.109787,13.59133],[124.109657,13.59094],[124.109627,13.59091],[124.109352,13.5912],[124.10881,13.59164],[124.108429,13.591858],[124.107086,13.592082],[124.10627,13.592515],[124.105774,13.592813],[124.105873,13.59308],[124.105957,13.59333]]]]}}