{"type":"Feature","properties":{"type":"barangay","level":"4","label":"Cawit Extension, Magallanes, Sorsogon, Bicol Region (Region V), PH","locale":"ph.bicol-region-region-v.sorsogon.magallanes.cawit-extension","country_id":177,"country_reference":177,"country_name":"Philippines","region_id":"2","region_reference":"5","region_name":"Bicol Region (Region V)","province_id":"70","province_reference":"70","province_name":"Sorsogon","city_id":"1490","city_reference":"1424","city_name":"Magallanes","barangay_id":"21353","barangay_reference":"36887","barangay_name":"Cawit Extension"},"geometry":{"type":"MultiPolygon","coordinates":[[[[123.84024,12.82754],[123.842216,12.82556],[123.842392,12.82556],[123.841957,12.82513],[123.841148,12.82433],[123.840607,12.82386],[123.839737,12.82306],[123.839462,12.82257],[123.839287,12.82156],[123.839333,12.82135],[123.838882,12.82112],[123.838333,12.82167],[123.838333,12.82194],[123.837784,12.8225],[123.837784,12.82278],[123.837097,12.82345],[123.837334,12.8241],[123.837997,12.82554],[123.839279,12.82679],[123.839333,12.82693],[123.839653,12.82716],[123.84024,12.82754]]]]}}