{"type":"Feature","properties":{"type":"barangay","level":"4","label":"Barangay II, Quezon, Quezon, CALABARZON (Region IV-A), PH","locale":"ph.calabarzon-region-iv-a.quezon.quezon.barangay-ii","country_id":177,"country_reference":177,"country_name":"Philippines","region_id":"4","region_reference":"41","region_name":"CALABARZON (Region IV-A)","province_id":"62","province_reference":"62","province_name":"Quezon","city_id":"1072","city_reference":"1316","city_name":"Quezon","barangay_id":"30511","barangay_reference":"34244","barangay_name":"Barangay II"},"geometry":{"type":"MultiPolygon","coordinates":[[[[122.185478,14.006666],[122.185524,14.006151],[122.185577,14.00546],[122.185593,14.005025],[122.184708,14.005021],[122.184128,14.004997],[122.181824,14.0061],[122.183708,14.006118],[122.183685,14.006558],[122.185478,14.006666]]]]}}