{"type":"Feature","properties":{"type":"barangay","level":"4","label":"Rang-ay, Cabatuan, Isabela, Cagayan Valley (Region II), PH","locale":"ph.cagayan-valley-region-ii.isabela.cabatuan.rang-ay","country_id":177,"country_reference":177,"country_name":"Philippines","region_id":"3","region_reference":"2","region_name":"Cagayan Valley (Region II)","province_id":"37","province_reference":"37","province_name":"Isabela","city_id":"268","city_reference":"697","city_name":"Cabatuan","barangay_id":"7173","barangay_reference":"17526","barangay_name":"Rang-ay"},"geometry":{"type":"MultiPolygon","coordinates":[[[[121.61676,16.94533],[121.616493,16.94739],[121.616989,16.948851],[121.618813,16.949909],[121.620659,16.95026],[121.622047,16.95031],[121.632317,16.925091],[121.632957,16.92341],[121.627274,16.91815],[121.623581,16.92687],[121.622818,16.92952],[121.62072,16.93458],[121.620979,16.93475],[121.617813,16.94372],[121.61676,16.94533]]]]}}