{"type":"Feature","properties":{"type":"barangay","level":"4","label":"Bangal, Dinalupihan, Bataan, Central Luzon (Region III), PH","locale":"ph.central-luzon-region-iii.bataan.dinalupihan.bangal","country_id":177,"country_reference":177,"country_name":"Philippines","region_id":"6","region_reference":"3","region_name":"Central Luzon (Region III)","province_id":"10","province_reference":"10","province_name":"Bataan","city_id":"418","city_reference":"138","city_name":"Dinalupihan","barangay_id":"11804","barangay_reference":"3090","barangay_name":"Bangal"},"geometry":{"type":"MultiPolygon","coordinates":[[[[120.351242,14.82911],[120.337898,14.82836],[120.338242,14.83371],[120.356056,14.84701],[120.351242,14.82911]]]]}}