{"type":"Feature","properties":{"type":"barangay","level":"4","label":"Cigaras, Magdalena, Laguna, CALABARZON (Region IV-A), PH","locale":"ph.calabarzon-region-iv-a.laguna.magdalena.cigaras","country_id":177,"country_reference":177,"country_name":"Philippines","region_id":"4","region_reference":"41","region_name":"CALABARZON (Region IV-A)","province_id":"40","province_reference":"40","province_name":"Laguna","city_id":"761","city_reference":"772","city_name":"Magdalena","barangay_id":"21406","barangay_reference":"19391","barangay_name":"Cigaras"},"geometry":{"type":"MultiPolygon","coordinates":[[[[121.442719,14.23241],[121.442467,14.22979],[121.440941,14.22663],[121.440041,14.22485],[121.438179,14.22406],[121.435539,14.2232],[121.43235,14.22295],[121.43084,14.2229],[121.430779,14.22251],[121.430344,14.22346],[121.430107,14.22649],[121.430107,14.2299],[121.429939,14.23139],[121.431641,14.23134],[121.435631,14.2316],[121.436539,14.23162],[121.438591,14.23198],[121.442719,14.23241]]]]}}