{"type":"Feature","properties":{"type":"barangay","level":"4","label":"Barangay 4, Catanauan, Quezon, CALABARZON (Region IV-A), PH","locale":"ph.calabarzon-region-iv-a.quezon.catanauan.barangay-4","country_id":177,"country_reference":177,"country_name":"Philippines","region_id":"4","region_reference":"41","region_name":"CALABARZON (Region IV-A)","province_id":"62","province_reference":"62","province_name":"Quezon","city_id":"337","city_reference":"1293","city_name":"Catanauan","barangay_id":"9310","barangay_reference":"33577","barangay_name":"Barangay 4"},"geometry":{"type":"MultiPolygon","coordinates":[[[[122.319344,13.59442],[122.319191,13.59198],[122.318764,13.59269],[122.318153,13.59282],[122.317253,13.59368],[122.316933,13.59433],[122.317322,13.59476],[122.31842,13.59465],[122.319344,13.59442]]]]}}