{"type":"Feature","properties":{"type":"barangay","level":"4","label":"San Roque, Las Nieves, Agusan del Norte, Caraga (Region XIII), PH","locale":"ph.caraga-region-xiii.agusan-del-norte.las-nieves.san-roque","country_id":177,"country_reference":177,"country_name":"Philippines","region_id":"5","region_reference":"13","region_name":"Caraga (Region XIII)","province_id":"2","province_reference":"2","province_name":"Agusan del Norte","city_id":"663","city_reference":"34","city_name":"Las Nieves","barangay_id":"18566","barangay_reference":"495","barangay_name":"San Roque"},"geometry":{"type":"MultiPolygon","coordinates":[[[[125.651321,8.74064],[125.653526,8.74447],[125.660278,8.73898],[125.66423,8.72682],[125.674652,8.69828],[125.660362,8.69847],[125.655617,8.69867],[125.653473,8.71058],[125.651093,8.72363],[125.651527,8.72746],[125.654083,8.72866],[125.654961,8.73134],[125.655403,8.73172],[125.655998,8.73318],[125.656677,8.73486],[125.654007,8.73794],[125.651321,8.74064]]]]}}