{"type":"Feature","properties":{"type":"barangay","level":"4","label":"Cambayog, Compostela, Cebu, Central Visayas (Region VII), PH","locale":"ph.central-visayas-region-vii.cebu.compostela.cambayog","country_id":177,"country_reference":177,"country_name":"Philippines","region_id":"7","region_reference":"7","region_name":"Central Visayas (Region VII)","province_id":"25","province_reference":"25","province_name":"Cebu","city_id":"1462","city_reference":"457","city_name":"Compostela","barangay_id":"10079","barangay_reference":"11206","barangay_name":"Cambayog"},"geometry":{"type":"MultiPolygon","coordinates":[[[[123.978302,10.47024],[123.979424,10.46945],[123.980751,10.46831],[123.983109,10.46675],[123.984612,10.46593],[123.985481,10.46545],[123.987801,10.46452],[123.990173,10.46383],[123.991997,10.46328],[123.992928,10.46282],[123.984917,10.45581],[123.979767,10.45137],[123.969131,10.46453],[123.978302,10.47024]]]]}}