{"type":"Feature","properties":{"type":"barangay","level":"4","label":"Tan-Awan, Loon, Bohol, Central Visayas (Region VII), PH","locale":"ph.central-visayas-region-vii.bohol.loon.tan-awan","country_id":177,"country_reference":177,"country_name":"Philippines","region_id":"7","region_reference":"7","region_name":"Central Visayas (Region VII)","province_id":"15","province_reference":"15","province_name":"Bohol","city_id":"710","city_reference":"240","city_name":"Loon","barangay_id":"19925","barangay_reference":"5515","barangay_name":"Tan-Awan"},"geometry":{"type":"MultiPolygon","coordinates":[[[[123.826218,9.78612],[123.828613,9.78151],[123.832787,9.77667],[123.825859,9.77064],[123.81321,9.7743],[123.814552,9.77731],[123.816261,9.77935],[123.826218,9.78612]]]]}}