{"type":"Feature","properties":{"type":"barangay","level":"4","label":"Angustias Zone II, Tayabas City, Quezon, CALABARZON (Region IV-A), PH","locale":"ph.calabarzon-region-iv-a.quezon.tayabas-city.angustias-zone-ii","country_id":177,"country_reference":177,"country_name":"Philippines","region_id":"4","region_reference":"41","region_name":"CALABARZON (Region IV-A)","province_id":"62","province_reference":"62","province_name":"Quezon","city_id":"1335","city_reference":"1325","city_name":"Tayabas City","barangay_id":"39332","barangay_reference":"34460","barangay_name":"Angustias Zone II"},"geometry":{"type":"MultiPolygon","coordinates":[[[[121.590897,14.03272],[121.59021,14.03189],[121.589981,14.03269],[121.590248,14.033],[121.590431,14.03321],[121.590897,14.03272]]]]}}