{"type":"Feature","properties":{"type":"barangay","level":"4","label":"Mangloy, Laak, Compostela Valley, Davao Region (Region XI), PH","locale":"ph.davao-region-region-xi.compostela-valley.laak.mangloy","country_id":177,"country_reference":177,"country_name":"Philippines","region_id":"9","region_reference":"11","region_name":"Davao Region (Region XI)","province_id":"26","province_reference":"26","province_name":"Compostela Valley","city_id":"627","city_reference":"495","city_name":"Laak","barangay_id":"17672","barangay_reference":"12020","barangay_name":"Mangloy"},"geometry":{"type":"MultiPolygon","coordinates":[[[[125.775383,7.76067],[125.773979,7.75903],[125.764427,7.75562],[125.754753,7.7518],[125.745934,7.74826],[125.744339,7.74521],[125.741348,7.73968],[125.738739,7.74076],[125.736771,7.74561],[125.734596,7.75023],[125.731483,7.75443],[125.731323,7.75737],[125.741722,7.75602],[125.755829,7.75783],[125.766968,7.75896],[125.775383,7.76067]]]]}}