{"type":"Feature","properties":{"type":"barangay","level":"4","label":"San Jose, Digos City, Davao del Sur, Davao Region (Region XI), PH","locale":"ph.davao-region-region-xi.davao-del-sur.digos-city.san-jose","country_id":177,"country_reference":177,"country_name":"Philippines","region_id":"9","region_reference":"11","region_name":"Davao Region (Region XI)","province_id":"28","province_reference":"28","province_name":"Davao del Sur","city_id":"411","city_reference":"518","city_name":"Digos City","barangay_id":"11682","barangay_reference":"12653","barangay_name":"San Jose"},"geometry":{"type":"MultiPolygon","coordinates":[[[[125.352814,6.74263],[125.351997,6.73909],[125.350273,6.73323],[125.349152,6.73128],[125.343277,6.72792],[125.337646,6.7278],[125.335838,6.72766],[125.334641,6.72645],[125.334923,6.73178],[125.342613,6.7438],[125.342903,6.74704],[125.342613,6.75176],[125.346397,6.74867],[125.351883,6.74491],[125.352814,6.74263]]]]}}