{"type":"Feature","properties":{"type":"barangay","level":"4","label":"Libertad, Maslog, Eastern Samar, Eastern Visayas (Region VIII), PH","locale":"ph.eastern-visayas-region-viii.eastern-samar.maslog.libertad","country_id":177,"country_reference":177,"country_name":"Philippines","region_id":"10","region_reference":"8","region_name":"Eastern Visayas (Region VIII)","province_id":"31","province_reference":"31","province_name":"Eastern Samar","city_id":"846","city_reference":"563","city_name":"Maslog","barangay_id":"24419","barangay_reference":"13602","barangay_name":"Libertad"},"geometry":{"type":"MultiPolygon","coordinates":[[[[125.225113,12.14959],[125.190857,12.09881],[125.183197,12.11181],[125.173622,12.1303],[125.176262,12.1317],[125.178963,12.13408],[125.181793,12.13669],[125.183189,12.13957],[125.184174,12.14246],[125.187477,12.14381],[125.190697,12.14418],[125.193527,12.14611],[125.19545,12.14814],[125.197678,12.1491],[125.203781,12.16762],[125.225113,12.14959]]]]}}