{"type":"Feature","properties":{"type":"barangay","level":"4","label":"Barangay 3, Catubig, Northern Samar, Eastern Visayas (Region VIII), PH","locale":"ph.eastern-visayas-region-viii.northern-samar.catubig.barangay-3","country_id":177,"country_reference":177,"country_name":"Philippines","region_id":"10","region_reference":"8","region_name":"Eastern Visayas (Region VIII)","province_id":"54","province_reference":"54","province_name":"Northern Samar","city_id":"343","city_reference":"1100","city_name":"Catubig","barangay_id":"9537","barangay_reference":"28838","barangay_name":"Barangay 3"},"geometry":{"type":"MultiPolygon","coordinates":[[[[125.055161,12.40927],[125.054977,12.40874],[125.05011,12.41112],[125.050194,12.41146],[125.055161,12.40927]]]]}}