{"type":"Feature","properties":{"type":"barangay","level":"4","label":"Mercedes, Jiabong, Samar, Eastern Visayas (Region VIII), PH","locale":"ph.eastern-visayas-region-viii.samar.jiabong.mercedes","country_id":177,"country_reference":177,"country_name":"Philippines","region_id":"10","region_reference":"8","region_name":"Eastern Visayas (Region VIII)","province_id":"66","province_reference":"66","province_name":"Samar","city_id":"569","city_reference":"1373","city_name":"Jiabong","barangay_id":"16232","barangay_reference":"35626","barangay_name":"Mercedes"},"geometry":{"type":"MultiPolygon","coordinates":[[[[124.998802,11.92252],[124.983833,11.90614],[124.981468,11.90785],[124.973427,11.91086],[124.995209,11.93915],[124.998802,11.92252]]]]}}