{"type":"Feature","properties":{"type":"barangay","level":"4","label":"San Pedro, Albuera, Leyte, Eastern Visayas (Region VIII), PH","locale":"ph.eastern-visayas-region-viii.leyte.albuera.san-pedro","country_id":177,"country_reference":177,"country_name":"Philippines","region_id":"10","region_reference":"8","region_name":"Eastern Visayas (Region VIII)","province_id":"43","province_reference":"43","province_name":"Leyte","city_id":"24","city_reference":"858","city_name":"Albuera","barangay_id":"513","barangay_reference":"21565","barangay_name":"San Pedro"},"geometry":{"type":"MultiPolygon","coordinates":[[[[124.732483,10.91727],[124.730522,10.90364],[124.714363,10.9037],[124.702827,10.90375],[124.702751,10.90404],[124.702477,10.9048],[124.701714,10.90556],[124.701149,10.90618],[124.70108,10.90667],[124.700729,10.90701],[124.700569,10.90711],[124.700172,10.90736],[124.699837,10.90776],[124.699432,10.90827],[124.699203,10.90871],[124.698952,10.90909],[124.69873,10.90942],[124.699829,10.91229],[124.702637,10.91508],[124.70652,10.91665],[124.708633,10.91653],[124.732483,10.91727]]]]}}