{"type":"Feature","properties":{"type":"barangay","level":"4","label":"Mudboron, Alangalang, Leyte, Eastern Visayas (Region VIII), PH","locale":"ph.eastern-visayas-region-viii.leyte.alangalang.mudboron","country_id":177,"country_reference":177,"country_name":"Philippines","region_id":"10","region_reference":"8","region_name":"Eastern Visayas (Region VIII)","province_id":"43","province_reference":"43","province_name":"Leyte","city_id":"23","city_reference":"857","city_name":"Alangalang","barangay_id":"482","barangay_reference":"21534","barangay_name":"Mudboron"},"geometry":{"type":"MultiPolygon","coordinates":[[[[124.878479,11.20956],[124.874931,11.20329],[124.874336,11.20166],[124.875587,11.1977],[124.870277,11.19465],[124.865738,11.19266],[124.862991,11.19098],[124.8591,11.1887],[124.857964,11.19788],[124.857018,11.20256],[124.856888,11.20466],[124.85762,11.20651],[124.858543,11.2083],[124.860779,11.21163],[124.864487,11.21112],[124.868019,11.21136],[124.874046,11.21101],[124.87719,11.21073],[124.878479,11.20956]]]]}}