{"type":"Feature","properties":{"type":"barangay","level":"4","label":"Nangalisan, Santa Lucia, Ilocos Sur, Ilocos Region (Region I), PH","locale":"ph.ilocos-region-region-i.ilocos-sur.santa-lucia.nangalisan","country_id":177,"country_reference":177,"country_name":"Philippines","region_id":"11","region_reference":"1","region_name":"Ilocos Region (Region I)","province_id":"35","province_reference":"35","province_name":"Ilocos Sur","city_id":"1179","city_reference":"636","city_name":"Santa Lucia","barangay_id":"34945","barangay_reference":"15144","barangay_name":"Nangalisan"},"geometry":{"type":"MultiPolygon","coordinates":[[[[120.44313,17.1057],[120.443047,17.104719],[120.443489,17.10346],[120.44413,17.10055],[120.444588,17.098669],[120.441643,17.09885],[120.436043,17.09882],[120.43605,17.09886],[120.435768,17.09989],[120.435837,17.10026],[120.435837,17.101549],[120.435608,17.10194],[120.435547,17.10203],[120.435547,17.10306],[120.435493,17.10482],[120.435547,17.105961],[120.435753,17.10594],[120.44313,17.1057]]]]}}