{"type":"Feature","properties":{"type":"barangay","level":"4","label":"Elizabeth, Dingras, Ilocos Norte, Ilocos Region (Region I), PH","locale":"ph.ilocos-region-region-i.ilocos-norte.dingras.elizabeth","country_id":177,"country_reference":177,"country_name":"Philippines","region_id":"11","region_reference":"1","region_name":"Ilocos Region (Region I)","province_id":"34","province_reference":"34","province_name":"Ilocos Norte","city_id":"423","city_reference":"598","city_name":"Dingras","barangay_id":"11938","barangay_reference":"14299","barangay_name":"Elizabeth"},"geometry":{"type":"MultiPolygon","coordinates":[[[[120.738777,18.055901],[120.740196,18.0548],[120.743263,18.052931],[120.746674,18.05011],[120.746239,18.047029],[120.74601,18.043539],[120.745659,18.040751],[120.744919,18.035589],[120.743843,18.03684],[120.743057,18.038191],[120.733582,18.0502],[120.731949,18.060949],[120.73336,18.059771],[120.73497,18.058491],[120.738449,18.05615],[120.738777,18.055901]]]]}}