{"type":"Feature","properties":{"type":"barangay","level":"4","label":"Rizal, Santa, Ilocos Sur, Ilocos Region (Region I), PH","locale":"ph.ilocos-region-region-i.ilocos-sur.santa.rizal","country_id":177,"country_reference":177,"country_name":"Philippines","region_id":"11","region_reference":"1","region_name":"Ilocos Region (Region I)","province_id":"35","province_reference":"35","province_name":"Ilocos Sur","city_id":"1190","city_reference":"638","city_name":"Santa","barangay_id":"35249","barangay_reference":"15215","barangay_name":"Rizal"},"geometry":{"type":"MultiPolygon","coordinates":[[[[120.458183,17.54348],[120.458511,17.54579],[120.458687,17.54693],[120.458687,17.548059],[120.458946,17.549339],[120.480713,17.54155],[120.482811,17.540804],[120.481857,17.540131],[120.481407,17.539841],[120.480614,17.539339],[120.480133,17.53895],[120.479767,17.538179],[120.479591,17.538019],[120.478973,17.537781],[120.458183,17.54348]]]]}}