{"type":"Feature","properties":{"type":"barangay","level":"4","label":"Lasip, Malasiqui, Pangasinan, Ilocos Region (Region I), PH","locale":"ph.ilocos-region-region-i.pangasinan.malasiqui.lasip","country_id":177,"country_reference":177,"country_name":"Philippines","region_id":"11","region_reference":"1","region_name":"Ilocos Region (Region I)","province_id":"61","province_reference":"61","province_name":"Pangasinan","city_id":"786","city_reference":"1262","city_name":"Malasiqui","barangay_id":"22056","barangay_reference":"32590","barangay_name":"Lasip"},"geometry":{"type":"MultiPolygon","coordinates":[[[[120.45385,15.91101],[120.45472,15.90786],[120.454681,15.90725],[120.455147,15.90462],[120.454453,15.90203],[120.452164,15.9014],[120.44841,15.90039],[120.443962,15.89968],[120.442543,15.90284],[120.441879,15.90558],[120.44149,15.90668],[120.440697,15.90935],[120.441254,15.90918],[120.442993,15.90892],[120.444901,15.9086],[120.447441,15.90917],[120.44886,15.9098],[120.451286,15.91086],[120.453842,15.9114],[120.45385,15.91101]]]]}}