{"type":"Feature","properties":{"type":"barangay","level":"4","label":"Inanlorenzana, Bayambang, Pangasinan, Ilocos Region (Region I), PH","locale":"ph.ilocos-region-region-i.pangasinan.bayambang.inanlorenzana","country_id":177,"country_reference":177,"country_name":"Philippines","region_id":"11","region_reference":"1","region_name":"Ilocos Region (Region I)","province_id":"61","province_reference":"61","province_name":"Pangasinan","city_id":"187","city_reference":"1248","city_name":"Bayambang","barangay_id":"4814","barangay_reference":"32216","barangay_name":"Inanlorenzana"},"geometry":{"type":"MultiPolygon","coordinates":[[[[120.424789,15.80548],[120.424782,15.80527],[120.425041,15.80373],[120.426407,15.80058],[120.427551,15.79889],[120.428711,15.79635],[120.426247,15.79488],[120.425629,15.795],[120.422577,15.79347],[120.421532,15.79315],[120.420647,15.79299],[120.417557,15.79232],[120.41568,15.79204],[120.414513,15.79202],[120.412903,15.7965],[120.411087,15.80388],[120.414322,15.80459],[120.417542,15.80496],[120.420723,15.80485],[120.422394,15.80518],[120.424789,15.80548]]]]}}