{"type":"Feature","properties":{"type":"barangay","level":"4","label":"Warey, Malasiqui, Pangasinan, Ilocos Region (Region I), PH","locale":"ph.ilocos-region-region-i.pangasinan.malasiqui.warey","country_id":177,"country_reference":177,"country_name":"Philippines","region_id":"11","region_reference":"1","region_name":"Ilocos Region (Region I)","province_id":"61","province_reference":"61","province_name":"Pangasinan","city_id":"786","city_reference":"1262","city_name":"Malasiqui","barangay_id":"22093","barangay_reference":"32627","barangay_name":"Warey"},"geometry":{"type":"MultiPolygon","coordinates":[[[[120.43911,15.87534],[120.442947,15.86519],[120.436592,15.86206],[120.434837,15.86618],[120.430038,15.87031],[120.435249,15.87296],[120.435883,15.87357],[120.43911,15.87534]]]]}}