{"type":"Feature","properties":{"type":"barangay","level":"4","label":"Tampugo, Tagudin, Ilocos Sur, Ilocos Region (Region I), PH","locale":"ph.ilocos-region-region-i.ilocos-sur.tagudin.tampugo","country_id":177,"country_reference":177,"country_name":"Philippines","region_id":"11","region_reference":"1","region_name":"Ilocos Region (Region I)","province_id":"35","province_reference":"35","province_name":"Ilocos Sur","city_id":"1296","city_reference":"645","city_name":"Tagudin","barangay_id":"38227","barangay_reference":"15385","barangay_name":"Tampugo"},"geometry":{"type":"MultiPolygon","coordinates":[[[[120.446922,16.9806],[120.449409,16.980379],[120.449501,16.98033],[120.461304,16.978889],[120.460938,16.970341],[120.460037,16.970989],[120.45639,16.973],[120.454826,16.974119],[120.452026,16.97431],[120.450562,16.974581],[120.449699,16.97551],[120.448738,16.97731],[120.448631,16.97764],[120.447441,16.97813],[120.446342,16.978371],[120.446449,16.978991],[120.446663,16.97957],[120.446877,16.98016],[120.446922,16.9806]]]]}}