{"type":"Feature","properties":{"type":"barangay","level":"4","label":"Santa Maria, Dumaran, Palawan, MIMAROPA (Region IV-B), PH","locale":"ph.mimaropa-region-iv-b.palawan.dumaran.santa-maria","country_id":177,"country_reference":177,"country_name":"Philippines","region_id":"13","region_reference":"42","region_name":"MIMAROPA (Region IV-B)","province_id":"59","province_reference":"59","province_name":"Palawan","city_id":"444","city_reference":"1204","city_name":"Dumaran","barangay_id":"12553","barangay_reference":"31199","barangay_name":"Santa Maria"},"geometry":{"type":"MultiPolygon","coordinates":[[[[119.570091,10.53333],[119.567253,10.51455],[119.509941,10.4873],[119.502968,10.51665],[119.557854,10.56836],[119.570091,10.53333]]]]}}