{"type":"Feature","properties":{"type":"barangay","level":"4","label":"Mapula, Romblon, Romblon, MIMAROPA (Region IV-B), PH","locale":"ph.mimaropa-region-iv-b.romblon.romblon.mapula","country_id":177,"country_reference":177,"country_name":"Philippines","region_id":"13","region_reference":"42","region_name":"MIMAROPA (Region IV-B)","province_id":"65","province_reference":"65","province_name":"Romblon","city_id":"1086","city_reference":"1358","city_name":"Romblon","barangay_id":"31147","barangay_reference":"35057","barangay_name":"Mapula"},"geometry":{"type":"MultiPolygon","coordinates":[[[[122.282791,12.53577],[122.277481,12.53291],[122.274399,12.53075],[122.272308,12.52932],[122.270432,12.52788],[122.259377,12.53432],[122.259659,12.53466],[122.260002,12.53494],[122.260498,12.53528],[122.261337,12.53645],[122.261887,12.53741],[122.262032,12.53797],[122.262108,12.53914],[122.262108,12.53996],[122.282791,12.53577]]]]}}