{"type":"Feature","properties":{"type":"barangay","level":"4","label":"Itangil, Dumaran, Palawan, MIMAROPA (Region IV-B), PH","locale":"ph.mimaropa-region-iv-b.palawan.dumaran.itangil","country_id":177,"country_reference":177,"country_name":"Philippines","region_id":"13","region_reference":"42","region_name":"MIMAROPA (Region IV-B)","province_id":"59","province_reference":"59","province_name":"Palawan","city_id":"444","city_reference":"1204","city_name":"Dumaran","barangay_id":"12550","barangay_reference":"31196","barangay_name":"Itangil"},"geometry":{"type":"MultiPolygon","coordinates":[[[[119.557854,10.56836],[119.502968,10.51665],[119.494003,10.55156],[119.528458,10.56094],[119.557854,10.56836]]]]}}