{"type":"Feature","properties":{"type":"barangay","level":"4","label":"San Jose Poblacion, Paluan, Occidental Mindoro, MIMAROPA (Region IV-B), PH","locale":"ph.mimaropa-region-iv-b.occidental-mindoro.paluan.san-jose-poblacion","country_id":177,"country_reference":177,"country_name":"Philippines","region_id":"13","region_reference":"42","region_name":"MIMAROPA (Region IV-B)","province_id":"57","province_reference":"57","province_name":"Occidental Mindoro","city_id":"971","city_reference":"1172","city_name":"Paluan","barangay_id":"27650","barangay_reference":"30492","barangay_name":"San Jose Poblacion"},"geometry":{"type":"MultiPolygon","coordinates":[[[[120.495697,13.42865],[120.494263,13.42197],[120.493317,13.42],[120.489853,13.41677],[120.484123,13.41366],[120.476662,13.41252],[120.474022,13.41265],[120.469948,13.41136],[120.465408,13.40893],[120.465393,13.40939],[120.465401,13.40948],[120.465401,13.41044],[120.464561,13.41223],[120.463707,13.4136],[120.461998,13.4148],[120.472908,13.43164],[120.476402,13.43752],[120.495697,13.42865]]]]}}