{"type":"Feature","properties":{"type":"barangay","level":"4","label":"Catadman-Manabay, Ozamis City, Misamis Occidental, Northern Mindanao (Region X), PH","locale":"ph.northern-mindanao-region-x.misamis-occidental.ozamis-city.catadman-manabay","country_id":177,"country_reference":177,"country_name":"Philippines","region_id":"14","region_reference":"10","region_name":"Northern Mindanao (Region X)","province_id":"48","province_reference":"48","province_name":"Misamis Occidental","city_id":"947","city_reference":"977","city_name":"Ozamis City","barangay_id":"27109","barangay_reference":"26105","barangay_name":"Catadman-Manabay"},"geometry":{"type":"MultiPolygon","coordinates":[[[[123.85762,8.16042],[123.859352,8.15804],[123.858727,8.15777],[123.857887,8.15708],[123.857201,8.1568],[123.856361,8.15618],[123.855881,8.15541],[123.855743,8.15486],[123.855881,8.15368],[123.855759,8.15328],[123.854927,8.15174],[123.854439,8.15035],[123.854309,8.14948],[123.854286,8.14943],[123.853737,8.1489],[123.853394,8.14862],[123.853317,8.14779],[123.853287,8.14719],[123.853287,8.14715],[123.85273,8.14715],[123.851357,8.14689],[123.849167,8.14764],[123.85096,8.14959],[123.853043,8.15185],[123.854797,8.15453],[123.855637,8.15574],[123.856438,8.1571],[123.85762,8.16042]]]]}}