{"type":"Feature","properties":{"type":"barangay","level":"4","label":"Gumabon, Magsaysay, Misamis Oriental, Northern Mindanao (Region X), PH","locale":"ph.northern-mindanao-region-x.misamis-oriental.magsaysay.gumabon","country_id":177,"country_reference":177,"country_name":"Philippines","region_id":"14","region_reference":"10","region_name":"Northern Mindanao (Region X)","province_id":"49","province_reference":"49","province_name":"Misamis Oriental","city_id":"1492","city_reference":"1000","city_name":"Magsaysay","barangay_id":"21493","barangay_reference":"26688","barangay_name":"Gumabon"},"geometry":{"type":"MultiPolygon","coordinates":[[[[125.226158,8.89549],[125.230713,8.89086],[125.233437,8.8873],[125.238312,8.88269],[125.237747,8.88133],[125.237167,8.88075],[125.236717,8.88038],[125.235718,8.87942],[125.234863,8.87835],[125.234337,8.87761],[125.233109,8.87631],[125.231651,8.87435],[125.220863,8.88835],[125.221489,8.88964],[125.222191,8.89064],[125.223267,8.89172],[125.223953,8.89203],[125.22496,8.89252],[125.225243,8.89379],[125.225197,8.89446],[125.225487,8.89511],[125.226158,8.89549]]]]}}