{"type":"Feature","properties":{"type":"barangay","level":"4","label":"Barangay 88, Kalookan City, Metropolitan Manila, National Capital Region, PH","locale":"ph.national-capital-region.metropolitan-manila.kalookan-city.barangay-88","country_id":177,"country_reference":177,"country_name":"Philippines","region_id":"12","region_reference":"141","region_name":"National Capital Region","province_id":"47","province_reference":"47","province_name":"Metropolitan Manila","city_id":"598","city_reference":"950","city_name":"Kalookan City","barangay_id":"16934","barangay_reference":"24317","barangay_name":"Barangay 88"},"geometry":{"type":"MultiPolygon","coordinates":[[[[120.980087,14.65618],[120.980492,14.656172],[120.980751,14.656172],[120.981133,14.656172],[120.98185,14.656172],[120.982147,14.656172],[120.982246,14.65615],[120.9823,14.65602],[120.982307,14.65577],[120.984573,14.655762],[120.984589,14.65534],[120.984573,14.654871],[120.984573,14.654261],[120.983803,14.654301],[120.983101,14.65433],[120.983017,14.654421],[120.9823,14.654421],[120.981613,14.654421],[120.980873,14.654402],[120.980057,14.65439],[120.98008,14.656],[120.980087,14.65618]]]]}}