{"type":"Feature","properties":{"type":"barangay","level":"4","label":"Tagdo, Mambajao, Camiguin, Northern Mindanao (Region X), PH","locale":"ph.northern-mindanao-region-x.camiguin.mambajao.tagdo","country_id":177,"country_reference":177,"country_name":"Philippines","region_id":"14","region_reference":"10","region_name":"Northern Mindanao (Region X)","province_id":"21","province_reference":"21","province_name":"Camiguin","city_id":"801","city_reference":"387","city_name":"Mambajao","barangay_id":"22494","barangay_reference":"9139","barangay_name":"Tagdo"},"geometry":{"type":"MultiPolygon","coordinates":[[[[124.692574,9.24167],[124.681587,9.20547],[124.672737,9.21132],[124.673073,9.21243],[124.672852,9.2134],[124.672653,9.21394],[124.672508,9.21447],[124.673393,9.21616],[124.673523,9.21657],[124.673561,9.21766],[124.673698,9.21846],[124.674057,9.21935],[124.67424,9.22002],[124.674461,9.22069],[124.674637,9.22165],[124.674637,9.22292],[124.67765,9.2367],[124.68399,9.23875],[124.692574,9.24167]]]]}}