{"type":"Feature","properties":{"type":"barangay","level":"4","label":"Mohon, Panaon, Misamis Occidental, Northern Mindanao (Region X), PH","locale":"ph.northern-mindanao-region-x.misamis-occidental.panaon.mohon","country_id":177,"country_reference":177,"country_name":"Philippines","region_id":"14","region_reference":"10","region_name":"Northern Mindanao (Region X)","province_id":"48","province_reference":"48","province_name":"Misamis Occidental","city_id":"975","city_reference":"978","city_name":"Panaon","barangay_id":"27775","barangay_reference":"26148","barangay_name":"Mohon"},"geometry":{"type":"MultiPolygon","coordinates":[[[[123.843269,8.38456],[123.843269,8.38446],[123.843887,8.38342],[123.844467,8.38289],[123.844856,8.38252],[123.844872,8.382456],[123.842056,8.38137],[123.834648,8.378517],[123.834106,8.37899],[123.833107,8.37962],[123.832077,8.37988],[123.831741,8.38039],[123.832619,8.38174],[123.835648,8.38241],[123.843269,8.38456]]]]}}