{"type":"Feature","properties":{"type":"barangay","level":"4","label":"Lunen, Tupi, South Cotabato, SOCCSKSARGEN (Region XII), PH","locale":"ph.soccsksargen-region-xii.south-cotabato.tupi.lunen","country_id":177,"country_reference":177,"country_name":"Philippines","region_id":"15","region_reference":"12","region_name":"SOCCSKSARGEN (Region XII)","province_id":"71","province_reference":"71","province_name":"South Cotabato","city_id":"1386","city_reference":"1441","city_name":"Tupi","barangay_id":"40622","barangay_reference":"37306","barangay_name":"Lunen"},"geometry":{"type":"MultiPolygon","coordinates":[[[[124.930107,6.33224],[124.924339,6.32597],[124.924713,6.32317],[124.92466,6.32079],[124.925941,6.316],[124.926262,6.31338],[124.928223,6.30981],[124.929237,6.30597],[124.927696,6.30178],[124.926468,6.29832],[124.928337,6.2961],[124.929161,6.29352],[124.927391,6.28879],[124.915604,6.28556],[124.91201,6.28708],[124.909317,6.28989],[124.906319,6.2923],[124.902817,6.29463],[124.901314,6.29645],[124.898438,6.30156],[124.917679,6.34197],[124.920128,6.34384],[124.930107,6.33224]]]]}}