{"type":"Feature","properties":{"type":"barangay","level":"4","label":"Crispin Salazar South, Janiuay, Iloilo, Western Visayas (Region VI), PH","locale":"ph.western-visayas-region-vi.iloilo.janiuay.crispin-salazar-south","country_id":177,"country_reference":177,"country_name":"Philippines","region_id":"16","region_reference":"6","region_name":"Western Visayas (Region VI)","province_id":"36","province_reference":"36","province_name":"Iloilo","city_id":"564","city_reference":"668","city_name":"Janiuay","barangay_id":"16055","barangay_reference":"16304","barangay_name":"Crispin Salazar South"},"geometry":{"type":"MultiPolygon","coordinates":[[[[122.506577,10.95077],[122.507019,10.95034],[122.507797,10.95022],[122.507736,10.94996],[122.507683,10.9497],[122.506973,10.94984],[122.506897,10.94964],[122.506622,10.94974],[122.506271,10.94951],[122.506577,10.95077]]],[[[122.506577,10.95077],[122.506111,10.95155],[122.507233,10.95235],[122.508163,10.95297],[122.508133,10.95156],[122.50795,10.95114],[122.507141,10.95132],[122.506577,10.95077]]]]}}