{"type":"Feature","properties":{"type":"barangay","level":"4","label":"Biga-A, Sibalom, Antique, Western Visayas (Region VI), PH","locale":"ph.western-visayas-region-vi.antique.sibalom.biga-a","country_id":177,"country_reference":177,"country_name":"Philippines","region_id":"16","region_reference":"6","region_name":"Western Visayas (Region VI)","province_id":"6","province_reference":"6","province_name":"Antique","city_id":"1218","city_reference":"105","city_name":"Sibalom","barangay_id":"36126","barangay_reference":"2338","barangay_name":"Biga-A"},"geometry":{"type":"MultiPolygon","coordinates":[[[[122.000183,10.8235],[121.99942,10.82274],[121.999046,10.82214],[121.998756,10.8205],[121.998642,10.8167],[121.987038,10.82001],[121.993896,10.82723],[122.000183,10.8235]]]]}}