{"type":"Feature","properties":{"type":"barangay","level":"4","label":"Casalngan, Hamtic, Antique, Western Visayas (Region VI), PH","locale":"ph.western-visayas-region-vi.antique.hamtic.casalngan","country_id":177,"country_reference":177,"country_name":"Philippines","region_id":"16","region_reference":"6","region_name":"Western Visayas (Region VI)","province_id":"6","province_reference":"6","province_name":"Antique","city_id":"516","city_reference":"97","city_name":"Hamtic","barangay_id":"14556","barangay_reference":"2092","barangay_name":"Casalngan"},"geometry":{"type":"MultiPolygon","coordinates":[[[[122.033653,10.62358],[122.032623,10.62087],[122.035339,10.60933],[122.035316,10.60927],[122.022743,10.6087],[122.014862,10.60835],[122.012718,10.60909],[122.00985,10.61074],[122.006607,10.61284],[122.004829,10.61419],[122.003197,10.61615],[122.003723,10.61766],[122.003693,10.61978],[122.007263,10.61934],[122.010101,10.61951],[122.015617,10.61953],[122.018806,10.62],[122.018997,10.61996],[122.022919,10.61912],[122.025597,10.61853],[122.030891,10.62173],[122.030258,10.62188],[122.033653,10.62358]]]]}}