{"type":"Feature","properties":{"type":"barangay","level":"4","label":"Buhang, Hamtic, Antique, Western Visayas (Region VI), PH","locale":"ph.western-visayas-region-vi.antique.hamtic.buhang","country_id":177,"country_reference":177,"country_name":"Philippines","region_id":"16","region_reference":"6","region_name":"Western Visayas (Region VI)","province_id":"6","province_reference":"6","province_name":"Antique","city_id":"516","city_reference":"97","city_name":"Hamtic","barangay_id":"14549","barangay_reference":"2085","barangay_name":"Buhang"},"geometry":{"type":"MultiPolygon","coordinates":[[[[121.995377,10.74331],[121.99678,10.743],[121.999184,10.74057],[121.999977,10.74023],[121.999939,10.73959],[122.000107,10.73887],[122.000214,10.73814],[122.000778,10.7377],[122.006462,10.73357],[122.003387,10.73169],[121.998787,10.72897],[121.996979,10.72944],[121.995338,10.73025],[121.993553,10.73152],[121.991508,10.73361],[121.99099,10.73501],[121.990997,10.73582],[121.990829,10.7372],[121.995377,10.74331]]]]}}