{"type":"Feature","properties":{"type":"barangay","level":"4","label":"Zambowood, Zamboanga City, Zamboanga del Sur, Zamboanga Peninsula (Region IX), PH","locale":"ph.zamboanga-peninsula-region-ix.zamboanga-del-sur.zamboanga-city.zambowood","country_id":177,"country_reference":177,"country_name":"Philippines","region_id":"17","region_reference":"9","region_name":"Zamboanga Peninsula (Region IX)","province_id":"81","province_reference":"81","province_name":"Zamboanga del Sur","city_id":"1421","city_reference":"1631","city_name":"Zamboanga City","barangay_id":"41665","barangay_reference":"41545","barangay_name":"Zambowood"},"geometry":{"type":"MultiPolygon","coordinates":[[[[122.138527,6.9628],[122.140503,6.95915],[122.140892,6.95682],[122.141098,6.95218],[122.140862,6.94981],[122.14003,6.94621],[122.140053,6.94304],[122.140694,6.9404],[122.141197,6.93689],[122.140831,6.93335],[122.141144,6.93254],[122.138908,6.93099],[122.135262,6.93204],[122.133499,6.93221],[122.130539,6.93252],[122.127861,6.93181],[122.127457,6.9335],[122.127167,6.93501],[122.127068,6.93876],[122.127403,6.94155],[122.127083,6.94437],[122.127228,6.94878],[122.127838,6.95121],[122.12941,6.95636],[122.132347,6.96115],[122.138527,6.9628]]]]}}