{"type":"Feature","properties":{"type":"barangay","level":"4","label":"Sandayong, Tampilisan, Zamboanga del Norte, Zamboanga Peninsula (Region IX), PH","locale":"ph.zamboanga-peninsula-region-ix.zamboanga-del-norte.tampilisan.sandayong","country_id":177,"country_reference":177,"country_name":"Philippines","region_id":"17","region_reference":"9","region_name":"Zamboanga Peninsula (Region IX)","province_id":"80","province_reference":"80","province_name":"Zamboanga del Norte","city_id":"1316","city_reference":"1602","city_name":"Tampilisan","barangay_id":"38729","barangay_reference":"40760","barangay_name":"Sandayong"},"geometry":{"type":"MultiPolygon","coordinates":[[[[122.712738,7.97235],[122.714363,7.97331],[122.715286,7.97115],[122.714928,7.96985],[122.714722,7.96913],[122.715073,7.96711],[122.715286,7.96591],[122.71698,7.96442],[122.717957,7.96271],[122.718468,7.96112],[122.722092,7.93934],[122.719719,7.9383],[122.711403,7.93596],[122.710533,7.94299],[122.710518,7.94304],[122.709641,7.95012],[122.709343,7.9517],[122.709137,7.95279],[122.706207,7.95473],[122.704536,7.97241],[122.712738,7.97235]]]]}}